Workbook

Sheet PLAN DE CUENTAS
A1: CONTABILIDAD COMPUTARIZADA - ING. CRISTHIAN SAIQUITA
B2: PLAN DE CUENTAS
A4: CUENTA | B4: DESCRIPCION | C4: TIPO | D4: 1D | E4: 2D
A5: 1 | B5: ACTIVO | C5: 1 | D5: 1 | E5: 10
A6: 1.1 | B6: ACTIVO CORRIENTE | C6: 1 | D6: 1 | E6: 10
A7: 1.1.1 | B7: ACTIVO DISPONIBLE | C7: 1 | D7: 1 | E7: 10
A8: 1.1.1.01 | B8: CAJA MONEDA NACIONAL | C8: 1 | D8: 1 | E8: 10
A9: 1.1.1.02 | B9: FONDO FIJO DE CAJA CHICA | C9: 1 | D9: 1 | E9: 10
A10: 1.1.1.03 | B10: CAJA MONEDA EXTRANJERA | C10: 1 | D10: 1 | E10: 10
A11: 1.1.1.04 | B11: BANCO MONEDA NACIONAL | C11: 1 | D11: 1 | E11: 10
A12: 1.1.1.05 | B12: BANCO MONEDA EXTRANJERA | C12: 1 | D12: 1 | E12: 10
A13: 1.1.1.06 | B13: DEPOSITOS DE CAJA DE AHORRO | C13: 1 | D13: 1 | E13: 10
A14: 1.1.1.07 | B14: DEPOSITOS A PLAZO FIJO | C14: 1 | D14: 1 | E14: 10
A15: 1.1.2 | B15: ACTIVO EXIGIBLE | C15: 1 | D15: 1 | E15: 10
A16: 1.1.2.01 | B16: CUENTAS POR COBRAR | C16: 1 | D16: 1 | E16: 10
A17: 1.1.2.02 | B17: DOCUENTOS POR COBRAR | C17: 1 | D17: 1 | E17: 10
A18: 1.1.2.03 | B18: ANTICIPOS SOBRE SUELDOS | C18: 1 | D18: 1 | E18: 10
... A31: 1.1.3.05 | B31: MERCADERIAS EN MOSTRADOR | C31: 1 | D31: 1 | E31: 10
A32: 1.2 | B32: ACTIVO NO CORRIENTE | C32: 1 | D32: 1 | E32: 10
A33: 1.2.1 | B33: BIENES DE USO | C33: 1 | D33: 1 | E33: 10
A34: 1.2.1.01 | B34: TERRENOS | C34: 1 | D34: 1 | E34: 10
A35: 1.2.1.02 | B35: EDIFICIOS | C35: 1 | D35: 1 | E35: 10
A36: 1.2.1.03 | B36: MUEBLES Y ENSERES | C36: 1 | D36: 1 | E36: 10
A37: 1.2.1.04 | B37: VEHICULOS | C37: 1 | D37: 1 | E37: 10
A38: 1.2.1.05 | B38: EQUIPO DE COMPUTACION | C38: 1 | D38: 1 | E38: 10
A39: 1.2.1.06 | B39: EQUIPO DE LIMPIEZA | C39: 1 | D39: 1 | E39: 10
A40: 1.2.2 | B40: INVERSIONES | C40: 1 | D40: 1 | E40: 10
A41: 1.2.3 | B41: OTROS ACTIVOS | C41: 1 | D41: 1 | E41: 10
A42: 1.2.3.01 | B42: ACTIVOS DIFERIDOS | C42: 1 | D42: 1 | E42: 10
A43: 1.2.3.01.01 | B43: INVENTARIO MATERIAL DE ESCRITORIO | C43: 1 | D43: 1 | E43: 10
A44: 1.2.3.01.02 | B44: SEGUROS PAGADOS POR ADELANTADO | C44: 1 | D44: 1 | E44: 10
... A50: 1.2.3.02.01 | B50: EQUIPO DE COMPUTACION | C50: 1 | D50: 1 | E50: 10
A51: 2 | B51: PASIVO | C51: 2 | D51: 2 | E51: 20
A52: 2.1 | B52: PASIVO CORRIENTE | C52: 2 | D52: 2 | E52: 20
A53: 2.1.1 | B53: CUENTAS POR PAGAR M/N | C53: 2 | D53: 2 | E53: 20
A54: 2.1.2 | B54: CUENTAS POR PAGAR M/E | C54: 2 | D54: 2 | E54: 20
A55: 2.1.3 | B55: DOCUMENTOS POR PAGAR M/N | C55: 2 | D55: 2 | E55: 20
A56: 2.1.4 | B56: DOCUMENTOS POR PAGAR M/E | C56: 2 | D56: 2 | E56: 20
A57: 2.1.5 | B57: OBLIGACIONES CON EL PERSONAL | C57: 2 | D57: 2 | E57: 20
A58: 2.1.5.01 | B58: SUELDOS Y SALARIOS POR PAGAR | C58: 2 | D58: 2 | E58: 20
A59: 2.1.5.02 | B59: AGUINALDOS POR PAGAR | C59: 2 | D59: 2 | E59: 20
A60: 2.1.6 | B60: APORTES Y RENTENCIONES POR PAGAR | C60: 2 | D60: 2 | E60: 20
A61: 2.1.6.01 | B61: CAJA NACIONAL DE SALUD | C61: 2 | D61: 2 | E61: 20
A62: 2.1.6.02 | B62: FONDO NACIONAL DE VIVIENDA SOCIAL | C62: 2 | D62: 2 | E62: 20
A63: 2.1.6.03 | B63: INSTITUTO DE FORMACION Y CAPACITACION LABORAL | C63: 2 | D63: 2 | E63: 20
A64: 2.1.6.04 | B64: AFP | C64: 2 | D64: 2 | E64: 20
... A78: 2.1.11.03 | B78: ANTICIPO CLIENTES | C78: 2 | D78: 2 | E78: 20
A79: 2.2 | B79: PASIVO NO CORRIENTE | C79: 2 | D79: 2 | E79: 20
A80: 2.2.1 | B80: OBLIGACIONES BANCARIAS | C80: 2 | D80: 2 | E80: 20
A81: 2.3 | B81: PROVISIONES | C81: 2 | D81: 2 | E81: 20
A82: 2.3.1 | B82: PROVISION PARA CUENTAS INCOBRABLES | C82: 2 | D82: 2 | E82: 20
A83: 2.3.2 | B83: PROVISION PARA INDEMNIZACIONES | C83: 2 | D83: 2 | E83: 20
A84: 2.3.3 | B84: PROVISION PARA AGUINALDO | C84: 2 | D84: 2 | E84: 20
A85: 2.4 | B85: OTROS | C85: 2 | D85: 2 | E85: 20
A86: 2.5 | B86: DEPRECIACION ACUMULADA | C86: 2 | D86: 2 | E86: 20
A87: 2.5.1 | B87: DEPRECIACION ACUMULADA EDIFICIO | C87: 2 | D87: 2 | E87: 20
A88: 2.5.2 | B88: DEPRECIACION ACUMULADA MUEBLES Y ENSERES | C88: 2 | D88: 2 | E88: 20
A89: 2.5.3 | B89: DEPRECIACION ACUMULADA VEHICULO | C89: 2 | D89: 2 | E89: 20
A90: 2.5.4 | B90: DEPRECIACION ACUMULADA EQUIPO DE COMPUTACION | C90: 2 | D90: 2 | E90: 20
A91: 3 | B91: PATRIMONIO O CAPITAL CONTABLE | C91: 3 | D91: 3 | E91: 30
A92: 3.1 | B92: CAPITAL SOCIAL | C92: 3 | D92: 3 | E92: 30
A93: 3.2 | B93: AJUSTE DE CAPITAL | C93: 3 | D93: 3 | E93: 30
A94: 3.3 | B94: UTILIDADES RETENIDAS | C94: 3 | D94: 3 | E94: 30
A95: 3.4 | B95: PERDIDAS ACUMULADAS | C95: 3 | D95: 3 | E95: 30
A96: 3.5 | B96: UTILIDAD DE LA GESTION | C96: 3 | D96: 3 | E96: 30
A97: 3.6 | B97: PERDIDA DE LA GESTION | C97: 3 | D97: 3 | E97: 30
A98: 4 | B98: CUENTAS DE ORDEN | C98: 4 | D98: 4 | E98: 40
A99: 5 | B99: CUENTAS DE INGRESOS | C99: 5 | D99: 5 | E99: 50
A100: 5.1 | B100: INGRESOS | C100: 5 | D100: 5 | E100: 50
A101: 5.1.1 | B101: INGRESOS DE OPERACIÓN | C101: 5 | D101: 5 | E101: 50
A102: 5.1.1.01 | B102: VENTAS | C102: 5 | D102: 5 | E102: 50
A103: 5.1.2 | B103: OTROS INGRESOS | C103: 5 | D103: 5 | E103: 50
A104: 5.1.2.01 | B104: DESCUENTOS SOBRE COMPRAS | C104: 5 | D104: 5 | E104: 50
A105: 5.1.2.02 | B105: DEVOLUCION Y BONIFICACION SOBRE COMPRAS | C105: 5 | D105: 5 | E105: 50
A106: 5.1.2.03 | B106: ALQUILERES PERCIBIDOS | C106: 5 | D106: 5 | E106: 50
A107: 5.1.2.04 | B107: COMISIONES GANADAS | C107: 5 | D107: 5 | E107: 50
A108: 5.1.2.05 | B108: INTERESES GANADOS | C108: 5 | D108: 5 | E108: 50
A109: 5.1.2.06 | B109: AJUSTE POR INFLACION Y TENENCIA DE BIENES | C109: 5 | D109: 5 | E109: 50
A110: 5.1.2.07 | B110: DIFERENCIA DE CAMBIO M/N | C110: 5 | D110: 5 | E110: 50
A111: 5.1.2.08 | B111: GANANCIA EN VENTA DE BIENES DE USO | C111: 5 | D111: 5 | E111: 50
A112: 6 | B112: EGRESOS | C112: 6 | D112: 6 | E112: 60
A113: 6.1 | B113: COSTO MERCADERIAS VENDIDAS | C113: 6 | D113: 6 | E113: 60
A114: 6.2 | B114: DEVOLUCION Y BONIFICACION SOBRE VENTAS | C114: 6 | D114: 6 | E114: 60
A115: 6.3 | B115: DESCUENTOS SOBRE VENTAS | C115: 6 | D115: 6 | E115: 60
A116: 6.4 | B116: GASTOS DE OPERACIÓN | C116: 6 | D116: 6 | E116: 60
A117: 6.4.1 | B117: GASTOS ADMINISTRATIVOS Y DE VENTAS | C117: 6 | D117: 6 | E117: 60
A118: 6.4.1.01 | B118: ASEO Y LIMPIEZA | C118: 6 | D118: 6 | E118: 60
A119: 6.4.1.02 | B119: COMISIONES A VENDEDORES | C119: 6 | D119: 6 | E119: 60
A120: 6.4.1.03 | B120: DONACIONES Y OBSEQUIOS | C120: 6 | D120: 6 | E120: 60
A121: 6.4.1.04 | B121: FLETES SOBRE VENTAS | C121: 6 | D121: 6 | E121: 60
A122: 6.4.1.05 | B122: GASTOS DE EMPAQUE | C122: 6 | D122: 6 | E122: 60
A123: 6.4.1.06 | B123: MATERIAL DE ESCRITORIO | C123: 6 | D123: 6 | E123: 60
A124: 6.4.1.07 | B124: COMBUSTIBLES Y LUBRICANTES | C124: 6 | D124: 6 | E124: 60
A125: 6.4.2 | B125: IMPUESTOS FISCALES E INDIRECTOS | C125: 6 | D125: 6 | E125: 60
A126: 6.4.2.01 | B126: GASTO IT | C126: 6 | D126: 6 | E126: 60
A127: 6.4.2.02 | B127: SUELDOS Y SALARIOS | C127: 6 | D127: 6 | E127: 60

Sheet DIARIO
C2: LIBRO DIARIO | G2: DIFERENCIAS | H2: =+G3-H3 -> 0
F3: TOTALES | G3: =SUM(tdiario[DEBE]) -> 1701215.4 | H3: =SUM(tdiario[HABER]) -> 1701215.4
A5: NRO | B5: FECHA | C5: GLOSA | D5: OBS | E5: CUENTA | F5: DETALLE | G5: DEBE | H5: HABER
A6: 1 | B6: 45292 | C6: ASIENTO DE APERTURA | E6: 1.1.1.01 | F6: =IF(E6="","",VLOOKUP(tdiario[[#This Row],[CUENTA]],tcuentas[],2,FALSE)) -> CAJA MONEDA NACIONAL | G6: 140000
E7: 1.1.2.01 | F7: =IF(E7="","",VLOOKUP(tdiario[[#This Row],[CUENTA]],tcuentas[],2,FALSE)) -> CUENTAS POR COBRAR | G7: 13000
E8: 1.1.3.01 | F8: =IF(E8="","",VLOOKUP(tdiario[[#This Row],[CUENTA]],tcuentas[],2,FALSE)) -> INVENTARIO INICIAL | G8: 89000
E9: 1.2.1.01 | F9: =IF(E9="","",VLOOKUP(tdiario[[#This Row],[CUENTA]],tcuentas[],2,FALSE)) -> TERRENOS | G9: 25000
E10: 1.2.1.02 | F10: =IF(E10="","",VLOOKUP(tdiario[[#This Row],[CUENTA]],tcuentas[],2,FALSE)) -> EDIFICIOS | G10: 99000
E11: 1.2.1.04 | F11: =IF(E11="","",VLOOKUP(tdiario[[#This Row],[CUENTA]],tcuentas[],2,FALSE)) -> VEHICULOS | G11: 65000
E12: 1.2.1.03 | F12: =IF(E12="","",VLOOKUP(tdiario[[#This Row],[CUENTA]],tcuentas[],2,FALSE)) -> MUEBLES Y ENSERES | G12: 23000
E13: 2.1.3 | F13: =IF(E13="","",VLOOKUP(tdiario[[#This Row],[CUENTA]],tcuentas[],2,FALSE)) -> DOCUMENTOS POR PAGAR M/N | H13: 120000
E14: 3.1 | F14: =IF(E14="","",VLOOKUP(tdiario[[#This Row],[CUENTA]],tcuentas[],2,FALSE)) -> CAPITAL SOCIAL | H14: 334000
F15: =IF(E15="","",VLOOKUP(tdiario[[#This Row],[CUENTA]],tcuentas[],2,FALSE))
A16: 2 | B16: 45293 | C16: COMPRA DE MERCADERIA | E16: 1.1.3.02 | F16: =IF(E16="","",VLOOKUP(tdiario[[#This Row],[CUENTA]],tcuentas[],2,FALSE)) -> COMPRAS | G16: =H18-G17 -> 107010
E17: 1.1.2.06 | F17: =IF(E17="","",VLOOKUP(tdiario[[#This Row],[CUENTA]],tcuentas[],2,FALSE)) -> CREDITO FISCAL | G17: =H18*0.13 -> 15990
E18: 1.1.1.01 | F18: =IF(E18="","",VLOOKUP(tdiario[[#This Row],[CUENTA]],tcuentas[],2,FALSE)) -> CAJA MONEDA NACIONAL | H18: 123000
F19: =IF(E19="","",VLOOKUP(tdiario[[#This Row],[CUENTA]],tcuentas[],2,FALSE))
A20: 3 | B20: 45293 | C20: COMPRA DE MATERIAL DE LIMPIEZA | E20: 6.4.1.01 | F20: =IF(E20="","",VLOOKUP(tdiario[[#This Row],[CUENTA]],tcuentas[],2,FALSE)) -> ASEO Y LIMPIEZA | G20: =H22-G21 -> 1044
E21: 1.1.2.06 | F21: =IF(E21="","",VLOOKUP(tdiario[[#This Row],[CUENTA]],tcuentas[],2,FALSE)) -> CREDITO FISCAL | G21: =H22*0.13 -> 156
E22: 1.1.1.01 | F22: =IF(E22="","",VLOOKUP(tdiario[[#This Row],[CUENTA]],tcuentas[],2,FALSE)) -> CAJA MONEDA NACIONAL | H22: 1200
F23: =IF(E23="","",VLOOKUP(tdiario[[#This Row],[CUENTA]],tcuentas[],2,FALSE))
A24: 4 | B24: 45294 | C24: VENTA AL CONTADO | E24: 1.1.1.01 | F24: =IF(E24="","",VLOOKUP(tdiario[[#This Row],[CUENTA]],tcuentas[],2,FALSE)) -> CAJA MONEDA NACIONAL | G24: 160000
E25: 6.4.2.01 | F25: =IF(E25="","",VLOOKUP(tdiario[[#This Row],[CUENTA]],tcuentas[],2,FALSE)) -> GASTO IT | G25: =G24*0.03 -> 4800
E26: 5.1.1.01 | F26: =IF(E26="","",VLOOKUP(tdiario[[#This Row],[CUENTA]],tcuentas[],2,FALSE)) -> VENTAS | H26: =G24-H27 -> 139200
E27: 2.1.8 | F27: =IF(E27="","",VLOOKUP(tdiario[[#This Row],[CUENTA]],tcuentas[],2,FALSE)) -> DEBITO FISCAL | H27: =G24*0.13 -> 20800
E28: 2.1.7.06 | F28: =IF(E28="","",VLOOKUP(tdiario[[#This Row],[CUENTA]],tcuentas[],2,FALSE)) -> IT ACUMULADO POR PAGAR | H28: 4800
F29: =IF(E29="","",VLOOKUP(tdiario[[#This Row],[CUENTA]],tcuentas[],2,FALSE))
A30: 5 | B30: 45295 | C30: VENTA DE MERCADERIAS A CREDITO | E30: 1.1.2.01 | F30: =IF(E30="","",VLOOKUP(tdiario[[#This Row],[CUENTA]],tcuentas[],2,FALSE)) -> CUENTAS POR COBRAR | G30: 150000
E31: 6.4.2.01 | F31: =IF(E31="","",VLOOKUP(tdiario[[#This Row],[CUENTA]],tcuentas[],2,FALSE)) -> GASTO IT | G31: =G30*0.03 -> 4500
E32: 5.1.1.01 | F32: =IF(E32="","",VLOOKUP(tdiario[[#This Row],[CUENTA]],tcuentas[],2,FALSE)) -> VENTAS | H32: =G30-H33 -> 130500
E33: 2.1.8 | F33: =IF(E33="","",VLOOKUP(tdiario[[#This Row],[CUENTA]],tcuentas[],2,FALSE)) -> DEBITO FISCAL | H33: =G30*0.13 -> 19500
E34: 2.1.7.06 | F34: =IF(E34="","",VLOOKUP(tdiario[[#This Row],[CUENTA]],tcuentas[],2,FALSE)) -> IT ACUMULADO POR PAGAR | H34: 4500
F35: =IF(E35="","",VLOOKUP(tdiario[[#This Row],[CUENTA]],tcuentas[],2,FALSE))
A36: 6 | B36: 45296 | C36: DEVOL. SOBRE COMPRA | E36: 1.1.1.01 | F36: =IF(E36="","",VLOOKUP(tdiario[[#This Row],[CUENTA]],tcuentas[],2,FALSE)) -> CAJA MONEDA NACIONAL | G36: 12000
E37: 5.1.2.02 | F37: =IF(E37="","",VLOOKUP(tdiario[[#This Row],[CUENTA]],tcuentas[],2,FALSE)) -> DEVOLUCION Y BONIFICACION SOBRE COMPRAS | H37: =G36-H38 -> 10440
E38: 2.1.8 | F38: =IF(E38="","",VLOOKUP(tdiario[[#This Row],[CUENTA]],tcuentas[],2,FALSE)) -> DEBITO FISCAL | H38: =G36*0.13 -> 1560
F39: =IF(E39="","",VLOOKUP(tdiario[[#This Row],[CUENTA]],tcuentas[],2,FALSE))
A40: 7 | B40: 45297 | C40: VENTA DE MERCADERIAS AL CONTADO | E40: 1.1.1.01 | F40: =IF(E40="","",VLOOKUP(tdiario[[#This Row],[CUENTA]],tcuentas[],2,FALSE)) -> CAJA MONEDA NACIONAL | G40: 240000
E41: 6.4.2.01 | F41: =IF(E41="","",VLOOKUP(tdiario[[#This Row],[CUENTA]],tcuentas[],2,FALSE)) -> GASTO IT | G41: =G40*0.03 -> 7200
E42: 5.1.1.01 | F42: =IF(E42="","",VLOOKUP(tdiario[[#This Row],[CUENTA]],tcuentas[],2,FALSE)) -> VENTAS | H42: =G40-H43 -> 208800
E43: 2.1.8 | F43: =IF(E43="","",VLOOKUP(tdiario[[#This Row],[CUENTA]],tcuentas[],2,FALSE)) -> DEBITO FISCAL | H43: =G40*0.13 -> 31200
E44: 2.1.7.06 | F44: =IF(E44="","",VLOOKUP(tdiario[[#This Row],[CUENTA]],tcuentas[],2,FALSE)) -> IT ACUMULADO POR PAGAR | H44: 7200
F45: =IF(E45="","",VLOOKUP(tdiario[[#This Row],[CUENTA]],tcuentas[],2,FALSE))
A46: 8 | B46: 45664 | C46: VENTA DE MERCADERIAS | F46: =IF(E46="","",VLOOKUP(tdiario[[#This Row],[CUENTA]],tcuentas[],2,FALSE))
F47: =IF(E47="","",VLOOKUP(tdiario[[#This Row],[CUENTA]],tcuentas[],2,FALSE))
F48: =IF(E48="","",VLOOKUP(tdiario[[#This Row],[CUENTA]],tcuentas[],2,FALSE))
F49: =IF(E49="","",VLOOKUP(tdiario[[#This Row],[CUENTA]],tcuentas[],2,FALSE))
F50: =IF(E50="","",VLOOKUP(tdiario[[#This Row],[CUENTA]],tcuentas[],2,FALSE))
F51: =IF(E51="","",VLOOKUP(tdiario[[#This Row],[CUENTA]],tcuentas[],2,FALSE))
A52: 8 | B52: 45664 | C52: VENTA DE MERCADERIAS | E52: 1.1.1.01 | F52: =IF(E52="","",VLOOKUP(tdiario[[#This Row],[CUENTA]],tcuentas[],2,FALSE)) -> CAJA MONEDA NACIONAL | G52: 28500 | J52: 30000 | K52: 0.05 | L52: =J52*K52 -> 1500
E53: 6.3 | F53: =IF(E53="","",VLOOKUP(tdiario[[#This Row],[CUENTA]],tcuentas[],2,FALSE)) -> DESCUENTOS SOBRE VENTAS | G53: 1305 | J53: 1500 | K53: 0.13 | L53: =J53*K53 -> 195 | M53: CF | N53: =J53-L53 -> 1305
E54: 1.1.2.06 | F54: =IF(E54="","",VLOOKUP(tdiario[[#This Row],[CUENTA]],tcuentas[],2,FALSE)) -> CREDITO FISCAL | G54: 195 | J54: =J52-J53 -> 28500 | K54: CAJA
E55: 6.4.2.01 | F55: =IF(E55="","",VLOOKUP(tdiario[[#This Row],[CUENTA]],tcuentas[],2,FALSE)) -> GASTO IT | G55: =J56*0.03 -> 900
E56: 5.1.1.01 | F56: =IF(E56="","",VLOOKUP(tdiario[[#This Row],[CUENTA]],tcuentas[],2,FALSE)) -> VENTAS | H56: =J56*0.87 -> 26100 | J56: 30000 | K56: 5 % | L56: =J56*0.05 -> 1500 | M56: DESCUENTO
E57: 2.1.8 | F57: =IF(E57="","",VLOOKUP(tdiario[[#This Row],[CUENTA]],tcuentas[],2,FALSE)) -> DEBITO FISCAL | H57: =J56*0.13 -> 3900 | L57: =L56*0.13 -> 195 | M57: CF (13%)
E58: 2.1.7.06 | F58: =IF(E58="","",VLOOKUP(tdiario[[#This Row],[CUENTA]],tcuentas[],2,FALSE)) -> IT ACUMULADO POR PAGAR | H58: 900 | J58: =J56-L56 -> 28500 | L58: =L56-L57 -> 1305 | M58: NETO (87%)
F59: =IF(E59="","",VLOOKUP(tdiario[[#This Row],[CUENTA]],tcuentas[],2,FALSE))
A60: 9 | B60: 45299 | C60: COBRO DE LA DEUDA 4 DE ENERO 50% | E60: 1.1.1.01 | F60: =IF(E60="","",VLOOKUP(tdiario[[#This Row],[CUENTA]],tcuentas[],2,FALSE)) -> CAJA MONEDA NACIONAL | G60: 75000 | J60: 30000 | K60: =J60*0.03 -> 900 | L60: IT(3%)
E61: 1.1.2.01 | F61: =IF(E61="","",VLOOKUP(tdiario[[#This Row],[CUENTA]],tcuentas[],2,FALSE)) -> CUENTAS POR COBRAR | H61: 75000 | K61: =J60*0.13 -> 3900 | L61: DF(13%)
F62: =IF(E62="","",VLOOKUP(tdiario[[#This Row],[CUENTA]],tcuentas[],2,FALSE)) | K62: =J60-K61 -> 26100 | L62: NETO VENTAS
A63: 10 | B63: 45300 | C63: COMPRA DE TERRENO Y EQU. COMPT | E63: 1.2.1.01 | F63: =IF(E63="","",VLOOKUP(tdiario[[#This Row],[CUENTA]],tcuentas[],2,FALSE)) -> TERRENOS | G63: 10000
E64: 1.2.1.05 | F64: =IF(E64="","",VLOOKUP(tdiario[[#This Row],[CUENTA]],tcuentas[],2,FALSE)) -> EQUIPO DE COMPUTACION | G64: =13000*0.87 -> 11310
E65: 1.1.2.06 | F65: =IF(E65="","",VLOOKUP(tdiario[[#This Row],[CUENTA]],tcuentas[],2,FALSE)) -> CREDITO FISCAL | G65: =13000*0.13 -> 1690
E66: 1.1.1.01 | F66: =IF(E66="","",VLOOKUP(tdiario[[#This Row],[CUENTA]],tcuentas[],2,FALSE)) -> CAJA MONEDA NACIONAL | H66: 23000
F67: =IF(E67="","",VLOOKUP(tdiario[[#This Row],[CUENTA]],tcuentas[],2,FALSE))
A68: 11 | B68: 45301 | C68: COMPRA DE MERCADERIA | E68: 1.1.3.02 | F68: =IF(E68="","",VLOOKUP(tdiario[[#This Row],[CUENTA]],tcuentas[],2,FALSE)) -> COMPRAS | G68: =H70-G69 -> 43500
E69: 1.1.2.06 | F69: =IF(E69="","",VLOOKUP(tdiario[[#This Row],[CUENTA]],tcuentas[],2,FALSE)) -> CREDITO FISCAL | G69: =H70*0.13 -> 6500
E70: 1.1.1.01 | F70: =IF(E70="","",VLOOKUP(tdiario[[#This Row],[CUENTA]],tcuentas[],2,FALSE)) -> CAJA MONEDA NACIONAL | H70: 50000
F71: =IF(E71="","",VLOOKUP(tdiario[[#This Row],[CUENTA]],tcuentas[],2,FALSE))
A72: 12 | B72: 45302 | C72: COMPRA DE MERCADERIAS CON DSCT 2% | E72: 1.1.3.02 | F72: =IF(E72="","",VLOOKUP(tdiario[[#This Row],[CUENTA]],tcuentas[],2,FALSE)) -> COMPRAS | G72: =J72-G73 -> 68730 | J72: 79000 | K72: 2% | L72: =J72*0.02 -> 1580 | M72: =L72*0.13 -> 205.4 | N72: DF
E73: 1.1.2.06 | F73: =IF(E73="","",VLOOKUP(tdiario[[#This Row],[CUENTA]],tcuentas[],2,FALSE)) -> CREDITO FISCAL | G73: =J72*0.13 -> 10270 | J73: =J72-L72 -> 77420 | M73: =L72-M72 -> 1374.6 | N73: DSCT NETO
E74: 1.1.1.01 | F74: =IF(E74="","",VLOOKUP(tdiario[[#This Row],[CUENTA]],tcuentas[],2,FALSE)) -> CAJA MONEDA NACIONAL | H74: 77420
E75: 5.1.2.01 | F75: =IF(E75="","",VLOOKUP(tdiario[[#This Row],[CUENTA]],tcuentas[],2,FALSE)) -> DESCUENTOS SOBRE COMPRAS | H75: 1374.6
E76: 2.1.8 | F76: =IF(E76="","",VLOOKUP(tdiario[[#This Row],[CUENTA]],tcuentas[],2,FALSE)) -> DEBITO FISCAL | H76: 205.4
F77: =IF(E77="","",VLOOKUP(tdiario[[#This Row],[CUENTA]],tcuentas[],2,FALSE)) | K77: 0.7 | L77: IVA
A78: 13 | B78: 45303 | C78: COMPRA DE COMBUSTIBLE | E78: 6.4.1.07 | F78: =IF(E78="","",VLOOKUP(tdiario[[#This Row],[CUENTA]],tcuentas[],2,FALSE)) -> COMBUSTIBLES Y LUBRICANTES | G78: =H80-G79 -> 1136.25 | J78: 1250 | K78: =J78*0.7 -> 875 | L78: =K78*0.13 -> 113.75
E79: 1.1.2.06 | F79: =IF(E79="","",VLOOKUP(tdiario[[#This Row],[CUENTA]],tcuentas[],2,FALSE)) -> CREDITO FISCAL | G79: 113.75
E80: 2.1.1 | F80: =IF(E80="","",VLOOKUP(tdiario[[#This Row],[CUENTA]],tcuentas[],2,FALSE)) -> CUENTAS POR PAGAR M/N | H80: 1250
F81: =IF(E81="","",VLOOKUP(tdiario[[#This Row],[CUENTA]],tcuentas[],2,FALSE))
A82: 14 | B82: 45305 | C82: DEVOL. SOBRE VENTAS | E82: 6.2 | F82: =IF(E82="","",VLOOKUP(tdiario[[#This Row],[CUENTA]],tcuentas[],2,FALSE)) -> DEVOLUCION Y BONIFICACION SOBRE VENTAS | G82: =H84-G83 -> 10440
E83: 1.1.2.06 | F83: =IF(E83="","",VLOOKUP(tdiario[[#This Row],[CUENTA]],tcuentas[],2,FALSE)) -> CREDITO FISCAL | G83: =H84*0.13 -> 1560
E84: 1.1.1.01 | F84: =IF(E84="","",VLOOKUP(tdiario[[#This Row],[CUENTA]],tcuentas[],2,FALSE)) -> CAJA MONEDA NACIONAL | H84: 12000
F85: =IF(E85="","",VLOOKUP(tdiario[[#This Row],[CUENTA]],tcuentas[],2,FALSE))
A86: 15 | B86: 45307 | C86: COMPRA MERD. CONTADO 30% SALDO CREDITO | E86: 1.1.3.02 | F86: =IF(E86="","",VLOOKUP(tdiario[[#This Row],[CUENTA]],tcuentas[],2,FALSE)) -> COMPRAS | G86: =70000*0.87 -> 60900 | I86: 70000
E87: 1.1.2.06 | F87: =IF(E87="","",VLOOKUP(tdiario[[#This Row],[CUENTA]],tcuentas[],2,FALSE)) -> CREDITO FISCAL | G87: 9100
E88: 1.1.1.01 | F88: =IF(E88="","",VLOOKUP(tdiario[[#This Row],[CUENTA]],tcuentas[],2,FALSE)) -> CAJA MONEDA NACIONAL | H88: =70000*0.3 -> 21000
E89: 2.1.1 | F89: =IF(E89="","",VLOOKUP(tdiario[[#This Row],[CUENTA]],tcuentas[],2,FALSE)) -> CUENTAS POR PAGAR M/N | H89: =70000-H88 -> 49000
F90: =IF(E90="","",VLOOKUP(tdiario[[#This Row],[CUENTA]],tcuentas[],2,FALSE))
A91: 16 | B91: 45308 | C91: PAGO DE DEUDA 12/01 | E91: 2.1.1 | F91: =IF(E91="","",VLOOKUP(tdiario[[#This Row],[CUENTA]],tcuentas[],2,FALSE)) -> CUENTAS POR PAGAR M/N | G91: 1250
E92: 1.1.1.01 | F92: =IF(E92="","",VLOOKUP(tdiario[[#This Row],[CUENTA]],tcuentas[],2,FALSE)) -> CAJA MONEDA NACIONAL | H92: 1250
F93: =IF(E93="","",VLOOKUP(tdiario[[#This Row],[CUENTA]],tcuentas[],2,FALSE))
A94: 17 | B94: 45310 | C94: PAGO SUELDOS | E94: 6.4.2.02 | F94: =IF(E94="","",VLOOKUP(tdiario[[#This Row],[CUENTA]],tcuentas[],2,FALSE)) -> SUELDOS Y SALARIOS | G94: 50000
E95: 1.1.1.01 | F95: =IF(E95="","",VLOOKUP(tdiario[[#This Row],[CUENTA]],tcuentas[],2,FALSE)) -> CAJA MONEDA NACIONAL | H95: 50000
F96: =IF(E96="","",VLOOKUP(tdiario[[#This Row],[CUENTA]],tcuentas[],2,FALSE))
A97: 18 | B97: 45311 | C97: VENTA CON DESCUENTO | E97: 1.1.1.01 | F97: =IF(E97="","",VLOOKUP(tdiario[[#This Row],[CUENTA]],tcuentas[],2,FALSE)) -> CAJA MONEDA NACIONAL | G97: 48500 | J97: TOTAL | K97: 0.03 | L97: CF | M97: DESC NETO
E98: 6.3 | F98: =IF(E98="","",VLOOKUP(tdiario[[#This Row],[CUENTA]],tcuentas[],2,FALSE)) -> DESCUENTOS SOBRE VENTAS | G98: 1305 | J98: 50000 | K98: =J98*0.03 -> 1500 | L98: =K98*0.13 -> 195 | M98: =K98-L98 -> 1305
E99: 1.1.2.06 | F99: =IF(E99="","",VLOOKUP(tdiario[[#This Row],[CUENTA]],tcuentas[],2,FALSE)) -> CREDITO FISCAL | G99: 195 | J99: =J98-K98 -> 48500 | K99: CAJA
E100: 6.4.2.01 | F100: =IF(E100="","",VLOOKUP(tdiario[[#This Row],[CUENTA]],tcuentas[],2,FALSE)) -> GASTO IT | G100: 1500 | K100: IT | L100: DF | M100: VENTA
E101: 5.1.1.01 | F101: =IF(E101="","",VLOOKUP(tdiario[[#This Row],[CUENTA]],tcuentas[],2,FALSE)) -> VENTAS | H101: =J101-L101 -> 43500 | J101: 50000 | K101: =J101*0.03 -> 1500 | L101: =J101*0.13 -> 6500 | M101: =J101-L101 -> 43500
E102: 2.1.8 | F102: =IF(E102="","",VLOOKUP(tdiario[[#This Row],[CUENTA]],tcuentas[],2,FALSE)) -> DEBITO FISCAL | H102: 6500
...

Sheet HOJA DE TRABAJO
B1: BALANCE DE COMPROBACION
E3: SUMAS | G3: SALDOS | I3: BALANCE GENERAL | K3: ER NATURALEZA | M3: ESTADO DE RESULTADOS
A4: CUENTA | B4: DETALLE | C4: X | D4: Y | E4: DEBE | F4: HABER | G4: DEUDOR | H4: ACREEDOR | I4: ACTIVO | J4: PASIVO | K4: PERDIDA | L4: GANACIA | M4: PERDIDA2 | N4: GANACIA3
A5: =+'PLAN DE CUENTAS'!A5 -> 1 | B5: =+'PLAN DE CUENTAS'!B5 -> ACTIVO | C5: =+'PLAN DE CUENTAS'!C5 -> 1 | D5: =IF(tbal[[#This Row],[DEBE]]+tbal[[#This Row],[HABER]]=0,"","X") | E5: =SUMIF(tdiario[CUENTA],tbal[[#This Row],[CUENTA]],tdiario[DEBE]) -> 0 | F5: =SUMIF(tdiario[CUENTA],tbal[[#This Row],[CUENTA]],tdiario[HABER]) -> 0 | G5: =IF(tbal[[#This Row],[DEBE]]-tbal[[#This Row],[HABER]]>0,tbal[[#This Row],[DEBE]]-tbal[[#This Row],[HABER]],0) -> 0 | H5: =IF(tbal[[#This Row],[HABER]]-tbal[[#This Row],[DEBE]]>0,tbal[[#This Row],[HABER]]-tbal[[#This Row],[DEBE]],0) -> 0 | I5: =IF((OR(tbal[[#This Row],[X]]=1,tbal[[#This Row],[X]]=2)),tbal[[#This Row],[DEUDOR]],0) -> 0 | J5: =IF((OR(tbal[[#This Row],[X]]=2,tbal[[#This Row],[X]]=3)),tbal[[#This Row],[ACREEDOR]],0) -> 0 | K5: =IF((OR(tbal[[#This Row],[X]]=3,tbal[[#This Row],[X]]=5)),tbal[[#This Row],[DEUDOR]],0) -> 0 | L5: =IF((OR(tbal[[#This Row],[X]]=3,tbal[[#This Row],[X]]=4)),tbal[[#This Row],[ACREEDOR]],0) -> 0 | M5: =IF((OR(tbal[[#This Row],[X]]=0,tbal[[#This Row],[X]]=6)),tbal[[#This Row],[DEUDOR]],0) -> 0 | N5: =IF((OR(tbal[[#This Row],[X]]=0,tbal[[#This Row],[X]]=5)),tbal[[#This Row],[ACREEDOR]],0) -> 0
A6: =+'PLAN DE CUENTAS'!A6 -> 1.1 | B6: =+'PLAN DE CUENTAS'!B6 -> ACTIVO CORRIENTE | C6: =+'PLAN DE CUENTAS'!C6 -> 1 | D6: =IF(tbal[[#This Row],[DEBE]]+tbal[[#This Row],[HABER]]=0,"","X") | E6: =SUMIF(tdiario[CUENTA],tbal[[#This Row],[CUENTA]],tdiario[DEBE]) -> 0 | F6: =SUMIF(tdiario[CUENTA],tbal[[#This Row],[CUENTA]],tdiario[HABER]) -> 0 | G6: =IF(tbal[[#This Row],[DEBE]]-tbal[[#This Row],[HABER]]>0,tbal[[#This Row],[DEBE]]-tbal[[#This Row],[HABER]],0) -> 0 | H6: =IF(tbal[[#This Row],[HABER]]-tbal[[#This Row],[DEBE]]>0,tbal[[#This Row],[HABER]]-tbal[[#This Row],[DEBE]],0) -> 0 | I6: =IF((OR(tbal[[#This Row],[X]]=1,tbal[[#This Row],[X]]=2)),tbal[[#This Row],[DEUDOR]],0) -> 0 | J6: =IF((OR(tbal[[#This Row],[X]]=2,tbal[[#This Row],[X]]=3)),tbal[[#This Row],[ACREEDOR]],0) -> 0 | K6: =IF((OR(tbal[[#This Row],[X]]=3,tbal[[#This Row],[X]]=5)),tbal[[#This Row],[DEUDOR]],0) -> 0 | L6: =IF((OR(tbal[[#This Row],[X]]=3,tbal[[#This Row],[X]]=4)),tbal[[#This Row],[ACREEDOR]],0) -> 0 | M6: =IF((OR(tbal[[#This Row],[X]]=0,tbal[[#This Row],[X]]=6)),tbal[[#This Row],[DEUDOR]],0) -> 0 | N6: =IF((OR(tbal[[#This Row],[X]]=0,tbal[[#This Row],[X]]=5)),tbal[[#This Row],[ACREEDOR]],0) -> 0
A7: =+'PLAN DE CUENTAS'!A7 -> 1.1.1 | B7: =+'PLAN DE CUENTAS'!B7 -> ACTIVO DISPONIBLE | C7: =+'PLAN DE CUENTAS'!C7 -> 1 | D7: =IF(tbal[[#This Row],[DEBE]]+tbal[[#This Row],[HABER]]=0,"","X") | E7: =SUMIF(tdiario[CUENTA],tbal[[#This Row],[CUENTA]],tdiario[DEBE]) -> 0 | F7: =SUMIF(tdiario[CUENTA],tbal[[#This Row],[CUENTA]],tdiario[HABER]) -> 0 | G7: =IF(tbal[[#This Row],[DEBE]]-tbal[[#This Row],[HABER]]>0,tbal[[#This Row],[DEBE]]-tbal[[#This Row],[HABER]],0) -> 0 | H7: =IF(tbal[[#This Row],[HABER]]-tbal[[#This Row],[DEBE]]>0,tbal[[#This Row],[HABER]]-tbal[[#This Row],[DEBE]],0) -> 0 | I7: =IF((OR(tbal[[#This Row],[X]]=1,tbal[[#This Row],[X]]=2)),tbal[[#This Row],[DEUDOR]],0) -> 0 | J7: =IF((OR(tbal[[#This Row],[X]]=2,tbal[[#This Row],[X]]=3)),tbal[[#This Row],[ACREEDOR]],0) -> 0 | K7: =IF((OR(tbal[[#This Row],[X]]=3,tbal[[#This Row],[X]]=5)),tbal[[#This Row],[DEUDOR]],0) -> 0 | L7: =IF((OR(tbal[[#This Row],[X]]=3,tbal[[#This Row],[X]]=4)),tbal[[#This Row],[ACREEDOR]],0) -> 0 | M7: =IF((OR(tbal[[#This Row],[X]]=0,tbal[[#This Row],[X]]=6)),tbal[[#This Row],[DEUDOR]],0) -> 0 | N7: =IF((OR(tbal[[#This Row],[X]]=0,tbal[[#This Row],[X]]=5)),tbal[[#This Row],[ACREEDOR]],0) -> 0
A8: =+'PLAN DE CUENTAS'!A8 -> 1.1.1.01 | B8: =+'PLAN DE CUENTAS'!B8 -> CAJA MONEDA NACIONAL | C8: =+'PLAN DE CUENTAS'!C8 -> 1 | D8: =IF(tbal[[#This Row],[DEBE]]+tbal[[#This Row],[HABER]]=0,"","X") -> X | E8: =SUMIF(tdiario[CUENTA],tbal[[#This Row],[CUENTA]],tdiario[DEBE]) -> 719000 | F8: =SUMIF(tdiario[CUENTA],tbal[[#This Row],[CUENTA]],tdiario[HABER]) -> 398715.65 | G8: =IF(tbal[[#This Row],[DEBE]]-tbal[[#This Row],[HABER]]>0,tbal[[#This Row],[DEBE]]-tbal[[#This Row],[HABER]],0) -> 320284.35 | H8: =IF(tbal[[#This Row],[HABER]]-tbal[[#This Row],[DEBE]]>0,tbal[[#This Row],[HABER]]-tbal[[#This Row],[DEBE]],0) -> 0 | I8: =IF((OR(tbal[[#This Row],[X]]=1,tbal[[#This Row],[X]]=2)),tbal[[#This Row],[DEUDOR]],0) -> 320284.35 | J8: =IF((OR(tbal[[#This Row],[X]]=2,tbal[[#This Row],[X]]=3)),tbal[[#This Row],[ACREEDOR]],0) -> 0 | K8: =IF((OR(tbal[[#This Row],[X]]=3,tbal[[#This Row],[X]]=5)),tbal[[#This Row],[DEUDOR]],0) -> 0 | L8: =IF((OR(tbal[[#This Row],[X]]=3,tbal[[#This Row],[X]]=4)),tbal[[#This Row],[ACREEDOR]],0) -> 0 | M8: =IF((OR(tbal[[#This Row],[X]]=0,tbal[[#This Row],[X]]=6)),tbal[[#This Row],[DEUDOR]],0) -> 0 | N8: =IF((OR(tbal[[#This Row],[X]]=0,tbal[[#This Row],[X]]=5)),tbal[[#This Row],[ACREEDOR]],0) -> 0
A9: =+'PLAN DE CUENTAS'!A9 -> 1.1.1.02 | B9: =+'PLAN DE CUENTAS'!B9 -> FONDO FIJO DE CAJA CHICA | C9: =+'PLAN DE CUENTAS'!C9 -> 1 | D9: =IF(tbal[[#This Row],[DEBE]]+tbal[[#This Row],[HABER]]=0,"","X") | E9: =SUMIF(tdiario[CUENTA],tbal[[#This Row],[CUENTA]],tdiario[DEBE]) -> 0 | F9: =SUMIF(tdiario[CUENTA],tbal[[#This Row],[CUENTA]],tdiario[HABER]) -> 0 | G9: =IF(tbal[[#This Row],[DEBE]]-tbal[[#This Row],[HABER]]>0,tbal[[#This Row],[DEBE]]-tbal[[#This Row],[HABER]],0) -> 0 | H9: =IF(tbal[[#This Row],[HABER]]-tbal[[#This Row],[DEBE]]>0,tbal[[#This Row],[HABER]]-tbal[[#This Row],[DEBE]],0) -> 0 | I9: =IF((OR(tbal[[#This Row],[X]]=1,tbal[[#This Row],[X]]=2)),tbal[[#This Row],[DEUDOR]],0) -> 0 | J9: =IF((OR(tbal[[#This Row],[X]]=2,tbal[[#This Row],[X]]=3)),tbal[[#This Row],[ACREEDOR]],0) -> 0 | K9: =IF((OR(tbal[[#This Row],[X]]=3,tbal[[#This Row],[X]]=5)),tbal[[#This Row],[DEUDOR]],0) -> 0 | L9: =IF((OR(tbal[[#This Row],[X]]=3,tbal[[#This Row],[X]]=4)),tbal[[#This Row],[ACREEDOR]],0) -> 0 | M9: =IF((OR(tbal[[#This Row],[X]]=0,tbal[[#This Row],[X]]=6)),tbal[[#This Row],[DEUDOR]],0) -> 0 | N9: =IF((OR(tbal[[#This Row],[X]]=0,tbal[[#This Row],[X]]=5)),tbal[[#This Row],[ACREEDOR]],0) -> 0
A10: =+'PLAN DE CUENTAS'!A10 -> 1.1.1.03 | B10: =+'PLAN DE CUENTAS'!B10 -> CAJA MONEDA EXTRANJERA | C10: =+'PLAN DE CUENTAS'!C10 -> 1 | D10: =IF(tbal[[#This Row],[DEBE]]+tbal[[#This Row],[HABER]]=0,"","X") | E10: =SUMIF(tdiario[CUENTA],tbal[[#This Row],[CUENTA]],tdiario[DEBE]) -> 0 | F10: =SUMIF(tdiario[CUENTA],tbal[[#This Row],[CUENTA]],tdiario[HABER]) -> 0 | G10: =IF(tbal[[#This Row],[DEBE]]-tbal[[#This Row],[HABER]]>0,tbal[[#This Row],[DEBE]]-tbal[[#This Row],[HABER]],0) -> 0 | H10: =IF(tbal[[#This Row],[HABER]]-tbal[[#This Row],[DEBE]]>0,tbal[[#This Row],[HABER]]-tbal[[#This Row],[DEBE]],0) -> 0 | I10: =IF((OR(tbal[[#This Row],[X]]=1,tbal[[#This Row],[X]]=2)),tbal[[#This Row],[DEUDOR]],0) -> 0 | J10: =IF((OR(tbal[[#This Row],[X]]=2,tbal[[#This Row],[X]]=3)),tbal[[#This Row],[ACREEDOR]],0) -> 0 | K10: =IF((OR(tbal[[#This Row],[X]]=3,tbal[[#This Row],[X]]=5)),tbal[[#This Row],[DEUDOR]],0) -> 0 | L10: =IF((OR(tbal[[#This Row],[X]]=3,tbal[[#This Row],[X]]=4)),tbal[[#This Row],[ACREEDOR]],0) -> 0 | M10: =IF((OR(tbal[[#This Row],[X]]=0,tbal[[#This Row],[X]]=6)),tbal[[#This Row],[DEUDOR]],0) -> 0 | N10: =IF((OR(tbal[[#This Row],[X]]=0,tbal[[#This Row],[X]]=5)),tbal[[#This Row],[ACREEDOR]],0) -> 0
A11: =+'PLAN DE CUENTAS'!A11 -> 1.1.1.04 | B11: =+'PLAN DE CUENTAS'!B11 -> BANCO MONEDA NACIONAL | C11: =+'PLAN DE CUENTAS'!C11 -> 1 | D11: =IF(tbal[[#This Row],[DEBE]]+tbal[[#This Row],[HABER]]=0,"","X") | E11: =SUMIF(tdiario[CUENTA],tbal[[#This Row],[CUENTA]],tdiario[DEBE]) -> 0 | F11: =SUMIF(tdiario[CUENTA],tbal[[#This Row],[CUENTA]],tdiario[HABER]) -> 0 | G11: =IF(tbal[[#This Row],[DEBE]]-tbal[[#This Row],[HABER]]>0,tbal[[#This Row],[DEBE]]-tbal[[#This Row],[HABER]],0) -> 0 | H11: =IF(tbal[[#This Row],[HABER]]-tbal[[#This Row],[DEBE]]>0,tbal[[#This Row],[HABER]]-tbal[[#This Row],[DEBE]],0) -> 0 | I11: =IF((OR(tbal[[#This Row],[X]]=1,tbal[[#This Row],[X]]=2)),tbal[[#This Row],[DEUDOR]],0) -> 0 | J11: =IF((OR(tbal[[#This Row],[X]]=2,tbal[[#This Row],[X]]=3)),tbal[[#This Row],[ACREEDOR]],0) -> 0 | K11: =IF((OR(tbal[[#This Row],[X]]=3,tbal[[#This Row],[X]]=5)),tbal[[#This Row],[DEUDOR]],0) -> 0 | L11: =IF((OR(tbal[[#This Row],[X]]=3,tbal[[#This Row],[X]]=4)),tbal[[#This Row],[ACREEDOR]],0) -> 0 | M11: =IF((OR(tbal[[#This Row],[X]]=0,tbal[[#This Row],[X]]=6)),tbal[[#This Row],[DEUDOR]],0) -> 0 | N11: =IF((OR(tbal[[#This Row],[X]]=0,tbal[[#This Row],[X]]=5)),tbal[[#This Row],[ACREEDOR]],0) -> 0
A12: =+'PLAN DE CUENTAS'!A12 -> 1.1.1.05 | B12: =+'PLAN DE CUENTAS'!B12 -> BANCO MONEDA EXTRANJERA | C12: =+'PLAN DE CUENTAS'!C12 -> 1 | D12: =IF(tbal[[#This Row],[DEBE]]+tbal[[#This Row],[HABER]]=0,"","X") | E12: =SUMIF(tdiario[CUENTA],tbal[[#This Row],[CUENTA]],tdiario[DEBE]) -> 0 | F12: =SUMIF(tdiario[CUENTA],tbal[[#This Row],[CUENTA]],tdiario[HABER]) -> 0 | G12: =IF(tbal[[#This Row],[DEBE]]-tbal[[#This Row],[HABER]]>0,tbal[[#This Row],[DEBE]]-tbal[[#This Row],[HABER]],0) -> 0 | H12: =IF(tbal[[#This Row],[HABER]]-tbal[[#This Row],[DEBE]]>0,tbal[[#This Row],[HABER]]-tbal[[#This Row],[DEBE]],0) -> 0 | I12: =IF((OR(tbal[[#This Row],[X]]=1,tbal[[#This Row],[X]]=2)),tbal[[#This Row],[DEUDOR]],0) -> 0 | J12: =IF((OR(tbal[[#This Row],[X]]=2,tbal[[#This Row],[X]]=3)),tbal[[#This Row],[ACREEDOR]],0) -> 0 | K12: =IF((OR(tbal[[#This Row],[X]]=3,tbal[[#This Row],[X]]=5)),tbal[[#This Row],[DEUDOR]],0) -> 0 | L12: =IF((OR(tbal[[#This Row],[X]]=3,tbal[[#This Row],[X]]=4)),tbal[[#This Row],[ACREEDOR]],0) -> 0 | M12: =IF((OR(tbal[[#This Row],[X]]=0,tbal[[#This Row],[X]]=6)),tbal[[#This Row],[DEUDOR]],0) -> 0 | N12: =IF((OR(tbal[[#This Row],[X]]=0,tbal[[#This Row],[X]]=5)),tbal[[#This Row],[ACREEDOR]],0) -> 0
A13: =+'PLAN DE CUENTAS'!A13 -> 1.1.1.06 | B13: =+'PLAN DE CUENTAS'!B13 -> DEPOSITOS DE CAJA DE AHORRO | C13: =+'PLAN DE CUENTAS'!C13 -> 1 | D13: =IF(tbal[[#This Row],[DEBE]]+tbal[[#This Row],[HABER]]=0,"","X") | E13: =SUMIF(tdiario[CUENTA],tbal[[#This Row],[CUENTA]],tdiario[DEBE]) -> 0 | F13: =SUMIF(tdiario[CUENTA],tbal[[#This Row],[CUENTA]],tdiario[HABER]) -> 0 | G13: =IF(tbal[[#This Row],[DEBE]]-tbal[[#This Row],[HABER]]>0,tbal[[#This Row],[DEBE]]-tbal[[#This Row],[HABER]],0) -> 0 | H13: =IF(tbal[[#This Row],[HABER]]-tbal[[#This Row],[DEBE]]>0,tbal[[#This Row],[HABER]]-tbal[[#This Row],[DEBE]],0) -> 0 | I13: =IF((OR(tbal[[#This Row],[X]]=1,tbal[[#This Row],[X]]=2)),tbal[[#This Row],[DEUDOR]],0) -> 0 | J13: =IF((OR(tbal[[#This Row],[X]]=2,tbal[[#This Row],[X]]=3)),tbal[[#This Row],[ACREEDOR]],0) -> 0 | K13: =IF((OR(tbal[[#This Row],[X]]=3,tbal[[#This Row],[X]]=5)),tbal[[#This Row],[DEUDOR]],0) -> 0 | L13: =IF((OR(tbal[[#This Row],[X]]=3,tbal[[#This Row],[X]]=4)),tbal[[#This Row],[ACREEDOR]],0) -> 0 | M13: =IF((OR(tbal[[#This Row],[X]]=0,tbal[[#This Row],[X]]=6)),tbal[[#This Row],[DEUDOR]],0) -> 0 | N13: =IF((OR(tbal[[#This Row],[X]]=0,tbal[[#This Row],[X]]=5)),tbal[[#This Row],[ACREEDOR]],0) -> 0
A14: =+'PLAN DE CUENTAS'!A14 -> 1.1.1.07 | B14: =+'PLAN DE CUENTAS'!B14 -> DEPOSITOS A PLAZO FIJO | C14: =+'PLAN DE CUENTAS'!C14 -> 1 | D14: =IF(tbal[[#This Row],[DEBE]]+tbal[[#This Row],[HABER]]=0,"","X") | E14: =SUMIF(tdiario[CUENTA],tbal[[#This Row],[CUENTA]],tdiario[DEBE]) -> 0 | F14: =SUMIF(tdiario[CUENTA],tbal[[#This Row],[CUENTA]],tdiario[HABER]) -> 0 | G14: =IF(tbal[[#This Row],[DEBE]]-tbal[[#This Row],[HABER]]>0,tbal[[#This Row],[DEBE]]-tbal[[#This Row],[HABER]],0) -> 0 | H14: =IF(tbal[[#This Row],[HABER]]-tbal[[#This Row],[DEBE]]>0,tbal[[#This Row],[HABER]]-tbal[[#This Row],[DEBE]],0) -> 0 | I14: =IF((OR(tbal[[#This Row],[X]]=1,tbal[[#This Row],[X]]=2)),tbal[[#This Row],[DEUDOR]],0) -> 0 | J14: =IF((OR(tbal[[#This Row],[X]]=2,tbal[[#This Row],[X]]=3)),tbal[[#This Row],[ACREEDOR]],0) -> 0 | K14: =IF((OR(tbal[[#This Row],[X]]=3,tbal[[#This Row],[X]]=5)),tbal[[#This Row],[DEUDOR]],0) -> 0 | L14: =IF((OR(tbal[[#This Row],[X]]=3,tbal[[#This Row],[X]]=4)),tbal[[#This Row],[ACREEDOR]],0) -> 0 | M14: =IF((OR(tbal[[#This Row],[X]]=0,tbal[[#This Row],[X]]=6)),tbal[[#This Row],[DEUDOR]],0) -> 0 | N14: =IF((OR(tbal[[#This Row],[X]]=0,tbal[[#This Row],[X]]=5)),tbal[[#This Row],[ACREEDOR]],0) -> 0
A15: =+'PLAN DE CUENTAS'!A15 -> 1.1.2 | B15: =+'PLAN DE CUENTAS'!B15 -> ACTIVO EXIGIBLE | C15: =+'PLAN DE CUENTAS'!C15 -> 1 | D15: =IF(tbal[[#This Row],[DEBE]]+tbal[[#This Row],[HABER]]=0,"","X") | E15: =SUMIF(tdiario[CUENTA],tbal[[#This Row],[CUENTA]],tdiario[DEBE]) -> 0 | F15: =SUMIF(tdiario[CUENTA],tbal[[#This Row],[CUENTA]],tdiario[HABER]) -> 0 | G15: =IF(tbal[[#This Row],[DEBE]]-tbal[[#This Row],[HABER]]>0,tbal[[#This Row],[DEBE]]-tbal[[#This Row],[HABER]],0) -> 0 | H15: =IF(tbal[[#This Row],[HABER]]-tbal[[#This Row],[DEBE]]>0,tbal[[#This Row],[HABER]]-tbal[[#This Row],[DEBE]],0) -> 0 | I15: =IF((OR(tbal[[#This Row],[X]]=1,tbal[[#This Row],[X]]=2)),tbal[[#This Row],[DEUDOR]],0) -> 0 | J15: =IF((OR(tbal[[#This Row],[X]]=2,tbal[[#This Row],[X]]=3)),tbal[[#This Row],[ACREEDOR]],0) -> 0 | K15: =IF((OR(tbal[[#This Row],[X]]=3,tbal[[#This Row],[X]]=5)),tbal[[#This Row],[DEUDOR]],0) -> 0 | L15: =IF((OR(tbal[[#This Row],[X]]=3,tbal[[#This Row],[X]]=4)),tbal[[#This Row],[ACREEDOR]],0) -> 0 | M15: =IF((OR(tbal[[#This Row],[X]]=0,tbal[[#This Row],[X]]=6)),tbal[[#This Row],[DEUDOR]],0) -> 0 | N15: =IF((OR(tbal[[#This Row],[X]]=0,tbal[[#This Row],[X]]=5)),tbal[[#This Row],[ACREEDOR]],0) -> 0
A16: =+'PLAN DE CUENTAS'!A16 -> 1.1.2.01 | B16: =+'PLAN DE CUENTAS'!B16 -> CUENTAS POR COBRAR | C16: =+'PLAN DE CUENTAS'!C16 -> 1 | D16: =IF(tbal[[#This Row],[DEBE]]+tbal[[#This Row],[HABER]]=0,"","X") -> X | E16: =SUMIF(tdiario[CUENTA],tbal[[#This Row],[CUENTA]],tdiario[DEBE]) -> 163000 | F16: =SUMIF(tdiario[CUENTA],tbal[[#This Row],[CUENTA]],tdiario[HABER]) -> 75000 | G16: =IF(tbal[[#This Row],[DEBE]]-tbal[[#This Row],[HABER]]>0,tbal[[#This Row],[DEBE]]-tbal[[#This Row],[HABER]],0) -> 88000 | H16: =IF(tbal[[#This Row],[HABER]]-tbal[[#This Row],[DEBE]]>0,tbal[[#This Row],[HABER]]-tbal[[#This Row],[DEBE]],0) -> 0 | I16: =IF((OR(tbal[[#This Row],[X]]=1,tbal[[#This Row],[X]]=2)),tbal[[#This Row],[DEUDOR]],0) -> 88000 | J16: =IF((OR(tbal[[#This Row],[X]]=2,tbal[[#This Row],[X]]=3)),tbal[[#This Row],[ACREEDOR]],0) -> 0 | K16: =IF((OR(tbal[[#This Row],[X]]=3,tbal[[#This Row],[X]]=5)),tbal[[#This Row],[DEUDOR]],0) -> 0 | L16: =IF((OR(tbal[[#This Row],[X]]=3,tbal[[#This Row],[X]]=4)),tbal[[#This Row],[ACREEDOR]],0) -> 0 | M16: =IF((OR(tbal[[#This Row],[X]]=0,tbal[[#This Row],[X]]=6)),tbal[[#This Row],[DEUDOR]],0) -> 0 | N16: =IF((OR(tbal[[#This Row],[X]]=0,tbal[[#This Row],[X]]=5)),tbal[[#This Row],[ACREEDOR]],0) -> 0
... A2644: =+'PLAN DE CUENTAS'!A2644 -> 0 | B2644: =+'PLAN DE CUENTAS'!B2644 -> 0 | C2644: =+'PLAN DE CUENTAS'!C2644 -> 0 | D2644: =IF(tbal[[#This Row],[DEBE]]+tbal[[#This Row],[HABER]]=0,"","X") | E2644: =SUMIF(tdiario[CUENTA],tbal[[#This Row],[CUENTA]],tdiario[DEBE]) -> 0 | F2644: =SUMIF(tdiario[CUENTA],tbal[[#This Row],[CUENTA]],tdiario[HABER]) -> 0 | G2644: =IF(tbal[[#This Row],[DEBE]]-tbal[[#This Row],[HABER]]>0,tbal[[#This Row],[DEBE]]-tbal[[#This Row],[HABER]],0) -> 0 | H2644: =IF(tbal[[#This Row],[HABER]]-tbal[[#This Row],[DEBE]]>0,tbal[[#This Row],[HABER]]-tbal[[#This Row],[DEBE]],0) -> 0 | I2644: =IF((OR(tbal[[#This Row],[X]]=1,tbal[[#This Row],[X]]=2)),tbal[[#This Row],[DEUDOR]],0) -> 0 | J2644: =IF((OR(tbal[[#This Row],[X]]=2,tbal[[#This Row],[X]]=3)),tbal[[#This Row],[ACREEDOR]],0) -> 0 | K2644: =IF((OR(tbal[[#This Row],[X]]=3,tbal[[#This Row],[X]]=5)),tbal[[#This Row],[DEUDOR]],0) -> 0 | L2644: =IF((OR(tbal[[#This Row],[X]]=3,tbal[[#This Row],[X]]=4)),tbal[[#This Row],[ACREEDOR]],0) -> 0 | M2644: =IF((OR(tbal[[#This Row],[X]]=0,tbal[[#This Row],[X]]=6)),tbal[[#This Row],[DEUDOR]],0) -> 0 | N2644: =IF((OR(tbal[[#This Row],[X]]=0,tbal[[#This Row],[X]]=5)),tbal[[#This Row],[ACREEDOR]],0) -> 0
B2645: TOTALES | E2645: =SUBTOTAL(109,tbal[DEBE]) -> 1701215.4 | F2645: =SUBTOTAL(109,tbal[HABER]) -> 1701215.4 | G2645: =SUBTOTAL(109,tbal[DEUDOR]) -> 1094864.6 | H2645: =SUBTOTAL(109,tbal[ACREEDOR]) -> 1094864.6 | I2645: =SUM(tbal[ACTIVO]) -> 1010734.3 | J2645: =SUM(tbal[PASIVO]) -> 521900 | K2645: =SUBTOTAL(109,tbal[PERDIDA]) -> 0 | L2645: =SUBTOTAL(109,tbal[GANACIA]) -> 334000 | M2645: =SUBTOTAL(109,tbal[PERDIDA2]) -> 84130.25 | N2645: =SUBTOTAL(109,tbal[GANACIA3]) -> 572964.6
A2646: UTLIDAD O PÉRDIDA DE LA GESTION | J2646: =M2646 -> 488834.35 | M2646: =tbal[[#Totals],[GANACIA3]]-tbal[[#Totals],[PERDIDA2]] -> 488834.35
A2647: TOTALES | I2647: =tbal[[#Totals],[ACTIVO]] -> 1010734.3 | J2647: =tbal[[#Totals],[PASIVO]]+J2646 -> 1010734.3 | M2647: =tbal[[#Totals],[PERDIDA2]]+M2646 -> 572964.6 | N2647: =tbal[[#Totals],[GANACIA3]] -> 572964.6

Sheet BALANCE GENERAL
C2: BALANCE GENERAL
C3: EMPRESA VIDA SRL
C4: EXPRESADO EN BS.
B6: ACTIVO
B7: =+'PLAN DE CUENTAS'!B6 -> ACTIVO CORRIENTE | F7: =E8+E12+E15 -> 777424.35
B8: =+'PLAN DE CUENTAS'!B7 -> ACTIVO DISPONIBLE | E8: 320284.35
B9: =+'PLAN DE CUENTAS'!B8 -> CAJA MONEDA NACIONAL | D9: 320284.35
B12: ACTIVO EXIGIBLE | E12: 88000
B13: CUENTAS POR COBRAR | D13: 88000
B15: ACTIVO REALIZABLE | E15: 369140
B16: INVENTARIO INICIAL | D16: 89000
B17: COMPRAS | D17: 280140
B19: ACTIVO NO CORRIENTE | F19: 233310
B20: BIENES DE USO | E20: 233310
B21: TERRENOS | D21: 35000
B22: EDIFICIOS | D22: 99000
B23: MUEBLES Y ENSERES | D23: 23000
B24: VEHICULOS | D24: 65000
B25: EQUIPO DE COMPUTACION | D25: 11310
B27: TOTAL ACTIVO | G27: =F19+F7 -> 1010734.3
B29: PASIVO Y CAPITAL | G29: =F30+F36 -> 1010734.3
B30: PASIVO | F30: =SUM(E31:E33) -> 187900
B31: PASIVO CORRIENTE | E31: =SUM(D32:D34) -> 187900
B32: CUENTAS POR PAGAR M/N | D32: 49000
B33: DOCUMENTOS POR PAGAR M/N | D33: 120000
B34: IT ACUMULADO POR PAGAR | D34: 18900
B36: PATRIMONIO O CAPITAL CONTABLE | F36: =D37+D38 -> 822834.35
B37: CAPITAL SOCIAL | D37: 334000
B38: UTILIDAD DE LA GESTION | D38: 488834.35
B40: PASIVO Y CAPITAL | G40: =G29 -> 1010734.3

Sheet ESTADO DE RESULTADOS
B2: ESTADO DE RESULTADOS
B3: EMPRESA COMERCIAL VIDA SRL
B4: EXPRESADO EN BS.
F6: =SUM(E7:E9) -> 572964.6
B7: VENTAS | E7: 548100
A9: más | B9: OTROS INRESOS | E9: 24864.6
B10: DESCUENTOS SOBRE COMPRAS | D10: 1374.6
B11: DEVOLUCION Y BONIFICACION SOBRE COMPRAS | D11: 23490
B13: UTILIDAD BRUTA EN VENTAS | E13: 572964.6
F14: =E15+E21 -> 84130.25
A15: menos | B15: GASTOS OPERATIVOS | E15: =D16+D17+D18+D19 -> 71080.25
B16: ASEO Y LIMPIEZA | D16: 1044
B17: COMBUSTIBLES Y LUBRICANTES | D17: 1136.25
B18: GASTO IT | D18: 18900
B19: SUELDOS Y SALARIOS | D19: 50000
A21: menos | B21: OTROS EGRESOS | E21: =D22+D23 -> 13050
B22: DEVOLUCION Y BONIFICACION SOBRE VENTAS | D22: 10440
B23: DESCUENTOS SOBRE VENTAS | D23: 2610
B25: UTILIDAD DE LA GESTION | F25: 488834.35
B26: IUE (25%) | F26: 122208.59
B27: UTILIDAD NETA | F27: 366625.76
